{
  "nodes": [
    {
      "type": "Ideal",
      "in": [
        0
      ],
      "out": [],
      "props": {
        "name": "Beauty",
        "scope": "",
        "success": ""
      }
    },
    {
      "type": "Action",
      "in": [
        1
      ],
      "out": [
        0
      ],
      "props": {
        "name": "Refactoring",
        "scope": "",
        "success": ""
      }
    },
    {
      "type": "Org",
      "in": [
        2
      ],
      "out": [
        1
      ],
      "props": {
        "name": "WyCash",
        "address": "",
        "scope": ""
      }
    },
    {
      "type": "Person",
      "in": [],
      "out": [
        2,
        3,
        4
      ],
      "props": {
        "name": "Ward",
        "address": "",
        "background": ""
      }
    },
    {
      "type": "Action",
      "in": [
        3
      ],
      "out": [],
      "props": {
        "name": "Mutation",
        "scope": "",
        "success": ""
      }
    },
    {
      "type": "Ideal",
      "in": [
        4
      ],
      "out": [],
      "props": {
        "name": "Beauty",
        "scope": "",
        "success": ""
      }
    }
  ],
  "rels": [
    {
      "type": "Serves",
      "from": 1,
      "to": 0,
      "props": {}
    },
    {
      "type": "Facilitates",
      "from": 2,
      "to": 1,
      "props": {}
    },
    {
      "type": "Serves",
      "from": 3,
      "to": 2,
      "props": {}
    },
    {
      "type": "Performs",
      "from": 3,
      "to": 4,
      "props": {}
    },
    {
      "type": "Holds",
      "from": 3,
      "to": 5,
      "props": {}
    }
  ]
}